vergeml/__init__.py
vergeml/__main__.py
vergeml/cache.py
vergeml/command.py
vergeml/config.py
vergeml/data.py
vergeml/dataset.py
vergeml/display.py
vergeml/env.py
vergeml/glossary.py
vergeml/img.py
vergeml/io.py
vergeml/libraries.py
vergeml/loader.py
vergeml/model.py
vergeml/operation.py
vergeml/option.py
vergeml/plugins.py
vergeml/random_robot.py
vergeml/results.py
vergeml/utils.py
vergeml/views.py
vergeml/wsgi.py
vergeml/commands/__init__.py
vergeml/commands/download.py
vergeml/commands/help.py
vergeml/commands/ls.py
vergeml/commands/new.py
vergeml/commands/plot.py
vergeml/commands/preprocess.py
vergeml/commands/run.py
vergeml/datasets/__init__.py
vergeml/datasets/cats_and_dogs.py
vergeml/datasets/celeba.py
vergeml/datasets/cifar_10.py
vergeml/datasets/cifar_100.py
vergeml/datasets/dogs.py
vergeml/datasets/fashion_mnist.py
vergeml/datasets/ham10000.py
vergeml/datasets/mnist.py
vergeml/datasets/svhn.py
vergeml/datasets/unique_objects.py
vergeml/models/__init__.py
vergeml/models/imagenet.py
vergeml/operations/__init__.py
vergeml/operations/augment.py
vergeml/operations/crop.py
vergeml/operations/flip_horizontal.py
vergeml/operations/flip_vertical.py
vergeml/operations/grayscale.py
vergeml/operations/random_crop.py
vergeml/operations/resize.py
vergeml/operations/rgb.py
vergeml/other/css/rest.css
vergeml/other/img/logo-big.png
vergeml/other/img/logo.png
vergeml/other/js/rest.js
vergeml/plots/__init__.py
vergeml/plots/confusion_matrix.py
vergeml/plots/pr.py
vergeml/plots/roc.py
vergeml/services/__init__.py
vergeml/services/rest.py
vergeml/services/tensorboard.py
vergeml/sources/__init__.py
vergeml/sources/features.py
vergeml/sources/image.py
vergeml/sources/labeled_image.py
vergeml/sources/mnist.py
vergeml-0.1.5.dist-info/LICENSE
vergeml-0.1.5.dist-info/METADATA
vergeml-0.1.5.dist-info/WHEEL
vergeml-0.1.5.dist-info/entry_points.txt
vergeml-0.1.5.dist-info/top_level.txt
vergeml-0.1.5.dist-info/RECORD
