Metadata-Version: 2.1
Name: vergeml
Version: 0.1.5
Summary: Machine Learning Environment
Home-page: http://github.com/vergeml/vergeml
Author: Markus Ecker
Author-email: markus.ecker@gmail.com
License: MIT
Keywords: ai deep learning
Platform: UNKNOWN
Classifier: Development Status :: 3 - Alpha
Classifier: Topic :: Utilities
Classifier: License :: OSI Approved :: MIT License
Requires-Dist: numpy
Requires-Dist: pyyaml
Requires-Dist: lz4
Requires-Dist: scikit-learn
Requires-Dist: Pillow
Requires-Dist: keras
Requires-Dist: waitress
Requires-Dist: matplotlib
